omsapi/__init__.py
omsapi-0.9.8.1.dist-info/METADATA
omsapi-0.9.8.1.dist-info/WHEEL
omsapi-0.9.8.1.dist-info/top_level.txt
omsapi-0.9.8.1.dist-info/RECORD
