Metadata-Version: 2.1
Name: omsapi
Version: 0.9.8.1
Summary: python client for OMS API
Home-page: https://gitlab.cern.ch/cmsoms/oms-api-client
Author: Mantas Stankevicius
Author-email: cmsoms-developers@cern.ch
Classifier: Programming Language :: Python :: 3
Classifier: Programming Language :: Python :: 3.6
Classifier: Programming Language :: Python :: 3.7
Classifier: Programming Language :: Python :: 3.8
Classifier: Programming Language :: Python :: 3.9
Classifier: Programming Language :: Python :: 3.10
Classifier: Programming Language :: Python :: 3.11
Classifier: Programming Language :: Python :: 3.12
Classifier: License :: OSI Approved :: MIT License
Classifier: Operating System :: OS Independent
Requires-Dist: requests
Requires-Dist: tsgauth
